rapidapi/__init__.py
django_rapidapi-0.1.0.dev1.dist-info/LICENSE
django_rapidapi-0.1.0.dev1.dist-info/WHEEL
django_rapidapi-0.1.0.dev1.dist-info/METADATA
django_rapidapi-0.1.0.dev1.dist-info/RECORD
