Metadata-Version: 2.1
Name: django-rapidapi
Version: 0.1.0.dev1
Summary: Django API extension
Home-page: https://github.com/antonrh/django-apirouter
License: MIT
Keywords: django,api,rest
Author: Anton Ruhlov
Author-email: antonruhlov@gmail.com
Requires-Python: >=3.6,<4.0
Classifier: License :: OSI Approved :: MIT License
Classifier: Programming Language :: Python :: 3
Classifier: Programming Language :: Python :: 3.6
Classifier: Programming Language :: Python :: 3.7
Classifier: Programming Language :: Python :: 3.8
Requires-Dist: django (>=3.1,<4.0)
Requires-Dist: mkdocs-material[docs] (>=5.5.9,<6.0.0)
Requires-Dist: mkdocs[docs] (>=1.1.2,<2.0.0)
Project-URL: Repository, https://github.com/antonrh/django-apirouter
